my_unique_rocket/__init__.py
my_unique_rocket/my_unique_rocket.py
my_unique_rocket/test_rocket.py
rocket/__init__.py
rocket/rocket.py
rocket/test_rocket.py
my_unique_rocket-1.0.1.dist-info/LICENSE.txt
my_unique_rocket-1.0.1.dist-info/METADATA
my_unique_rocket-1.0.1.dist-info/WHEEL
my_unique_rocket-1.0.1.dist-info/top_level.txt
my_unique_rocket-1.0.1.dist-info/RECORD
