Metadata-Version: 2.1
Name: my_unique_rocket
Version: 1.0.1
Summary: An awesome package that does something
Home-page: http://pypi.python.org/pypi/rocket/
Author: Chaib Fakhreddine
Author-email: fakhreddinechaib@gmail.com
License: LICENSE.txt
License-File: LICENSE.txt
